asy/__asy__.py
asy/__init__.py
asy/__main__.py
asy/cli.py
asy/components/__init__.py
asy/components/reloader.py
asy/components/timeout.py
asy/exceptions.py
asy/helpers.py
asy/normalizer.py
asy/protocols.py
asy/schedulable.py
asy/supervisor.py
asy/tokens.py
asy-0.0.7.dist-info/WHEEL
asy-0.0.7.dist-info/METADATA
asy-0.0.7.dist-info/RECORD
