Metadata-Version: 2.1
Name: asy
Version: 0.0.7
Summary: asy is easy and powerful supervisor for asyncio.
Home-page: https://github.com/sasano8/asy
License: MIT
Keywords: asyncio
Author: sasano8
Author-email: y-sasahara@ys-method.com
Requires-Python: >=3.8,<4.0
Classifier: License :: OSI Approved :: MIT License
Classifier: Programming Language :: Python :: 3
Classifier: Programming Language :: Python :: 3.8
Requires-Dist: typer (>=0.3.2,<0.4.0)
Project-URL: Repository, https://github.com/sasano8/asy
